docs/conf.py
docs/index.rst
docs/modules.rst
docs/requirements.txt
examples/example.py
examples/example_thermal.py
pyccx/__init__.py
pyccx/core.py
pyccx/version.py
pyccx/analysis/__init__.py
pyccx/analysis/analysis.py
pyccx/bc/__init__.py
pyccx/bc/boundarycondition.py
pyccx/loadcase/__init__.py
pyccx/loadcase/loadcase.py
pyccx/material/__init__.py
pyccx/material/material.py
pyccx/mesh/__init__.py
pyccx/mesh/elements.py
pyccx/mesh/mesh.py
pyccx/mesh/mesher.py
pyccx/mesh/utils.py
pyccx/results/__init__.py
pyccx/results/results.py
pyccx/utils/__init__.py
pyccx/utils/exporters.py
pyccx-0.2.0.dist-info/METADATA
pyccx-0.2.0.dist-info/WHEEL
pyccx-0.2.0.dist-info/licenses/LICENSE
pyccx-0.2.0.dist-info/RECORD
