Metadata-Version: 2.4
Name: PyCCX
Version: 0.2.0
Summary: Simulation and FEA environment for Python built upon Calculix and GMSH
Project-URL: Homepage, https://github.com/drlukeparry/pyccx
Project-URL: Documentation, https://pyccx.readthedocs.io/en/latest/
Project-URL: Source, https://github.com/drlukeparry/pyccx/
Project-URL: Tracker, https://github.com/drlukeparry/pyccx/issues
Author-email: Luke Parry <dev@lukeparry.uk>, Luktug <contact@luktug.co.uk>
License: Copyright (c) 2025, Luke Parry
License-File: LICENSE
Keywords: Calculix,FEA,Finite Element Analysis,GMSH,Simulation
Classifier: License :: OSI Approved :: BSD License
Classifier: Programming Language :: Python
Classifier: Programming Language :: Python :: 3.8
Classifier: Programming Language :: Python :: 3.9
Classifier: Programming Language :: Python :: 3.10
Classifier: Programming Language :: Python :: 3.11
Classifier: Programming Language :: Python :: 3.12
Classifier: Programming Language :: Python :: 3.13
Classifier: Topic :: Scientific/Engineering
Requires-Python: >=3.8
Requires-Dist: colorlog
Requires-Dist: gmsh>=4.14.0
Requires-Dist: matplotlib
Requires-Dist: numpy>1.21
Requires-Dist: setuptools
Provides-Extra: build
Requires-Dist: build; extra == 'build'
Requires-Dist: hatchling; extra == 'build'
Requires-Dist: requests; extra == 'build'
Requires-Dist: twine; extra == 'build'
Provides-Extra: codegen
Requires-Dist: numpy; extra == 'codegen'
Requires-Dist: pytest; extra == 'codegen'
Provides-Extra: docs
Requires-Dist: autodocsumm; extra == 'docs'
Requires-Dist: docutils==0.21.2; extra == 'docs'
Requires-Dist: furo; extra == 'docs'
Requires-Dist: jupyter; extra == 'docs'
Requires-Dist: m2r2==0.3.4; extra == 'docs'
Requires-Dist: matplotlib; extra == 'docs'
Requires-Dist: mock; extra == 'docs'
Requires-Dist: numpy; extra == 'docs'
Requires-Dist: pypandoc; extra == 'docs'
Requires-Dist: sphinx; extra == 'docs'
Requires-Dist: sphinx-autodoc-typehints; extra == 'docs'
Requires-Dist: sphinx-automodapi; extra == 'docs'
Requires-Dist: sphinx-paramlinks; extra == 'docs'
Requires-Dist: sphinx-rtd-theme; extra == 'docs'
Requires-Dist: trimesh; extra == 'docs'
Provides-Extra: lint
Requires-Dist: pre-commit; extra == 'lint'
Requires-Dist: ruff; extra == 'lint'
Provides-Extra: tests
Requires-Dist: coverage-badge; extra == 'tests'
Requires-Dist: pytest; extra == 'tests'
Requires-Dist: pytest-cov; extra == 'tests'
